scaling_vin_pytorch/__init__.py
scaling_vin_pytorch/vin.py
scaling_vin_pytorch/vin_3d.py
scaling_vin_pytorch-0.0.12.dist-info/METADATA
scaling_vin_pytorch-0.0.12.dist-info/WHEEL
scaling_vin_pytorch-0.0.12.dist-info/licenses/LICENSE
scaling_vin_pytorch-0.0.12.dist-info/RECORD
