Metadata-Version: 2.3
Name: scaling-vin-pytorch
Version: 0.0.12
Summary: Scaling Value Iteration Networks
Project-URL: Homepage, https://pypi.org/project/scaling-vin-pytorch/
Project-URL: Repository, https://github.com/lucidrains/scaling-vin-pytorch
Author-email: Phil Wang <lucidrains@gmail.com>
License: MIT License
License-File: LICENSE
Keywords: artificial intelligence,deep learning,planning,value iteration network
Classifier: Development Status :: 4 - Beta
Classifier: Intended Audience :: Developers
Classifier: License :: OSI Approved :: MIT License
Classifier: Programming Language :: Python :: 3.9
Classifier: Topic :: Scientific/Engineering :: Artificial Intelligence
Requires-Python: >=3.9
Requires-Dist: beartype
Requires-Dist: einops>=0.8.0
Requires-Dist: einx>=0.3.0
Requires-Dist: torch>=2.0
Requires-Dist: unfoldnd
Requires-Dist: x-transformers>=1.35.3
Provides-Extra: examples
Provides-Extra: test
Requires-Dist: pytest; extra == 'test'
